zuu_va/easyocr_.py
zuu_va/pillow_.py
zuu_va/pyautogui_.py
zuu_va/pygetwindow_.py
zuu_va/pyscreeze_.py
zuu_va/pywin32_.py
zuu_va/screeninfo_.py
zuu_va/timely_kill.py
zuu_va-0.1.0.dist-info/METADATA
zuu_va-0.1.0.dist-info/WHEEL
zuu_va-0.1.0.dist-info/licenses/LICENSE
zuu_va-0.1.0.dist-info/RECORD
