Metadata-Version: 2.3
Name: zuu-va
Version: 0.1.0
Summary: zuu for vision and automation
Author-email: ZackaryW <gitzackw@gmail.com>
Requires-Python: >=3.8
Requires-Dist: zuu>=3.0.0
